{
    "cargo": "Diretor",
    "projetos": [
        {
            "nome": "project_1"
        },
        {
            "nome": "project_2"
        },
        {
            "nome": "riomar"
        }
    ],
    "ranking":
        {
        "Produtividade": 8,
        "Qualidade": 10,
        "Trabalho Equipe": 5,
        "Cumprimento Prazos": 8.5,
        "Iniciativa": 9,
        "Gestao de Conflitos": 6,
        "Treinamento": 9,
        "EPI": 7,
        "Feedback": 8.5
    },
    
    "horas_extras": {
        "Jan": 5,
        "Fev": 4,
        "Mar": 7,
        "Abr": 10,
        "Mai": 5,
        "Jun": 8,
        "Jul": 0,
        "Aug": 2,
        "Set": 1,
        "Out": 4,
        "Nov": 8,
        "Dez": 6
    },

    "participacao_mercado_anual": {
        "2023": {
          "Obras": 15,
          "Software": 53,
          "Pesquisa": 17,
          "Marketing": 10,
          "Outras": 5
        }
      }
}